openadr3_client_gac_compliance/__init__.py
openadr3_client_gac_compliance/gac20/__init__.py
openadr3_client_gac_compliance/gac20/event_gac_compliant.py
openadr3_client_gac_compliance/gac20/plugin.py
openadr3_client_gac_compliance/gac20/program_gac_compliant.py
openadr3_client_gac_compliance/gac20/ven_gac_compliant.py
openadr3_client_gac_compliance/gac21/__init__.py
openadr3_client_gac_compliance-3.0.1.dist-info/METADATA
openadr3_client_gac_compliance-3.0.1.dist-info/WHEEL
openadr3_client_gac_compliance-3.0.1.dist-info/licenses/LICENSE.md
openadr3_client_gac_compliance-3.0.1.dist-info/RECORD
