Metadata-Version: 2.4
Name: openadr3-client-gac-compliance
Version: 3.0.1
Summary: 
License-File: LICENSE.md
Author: Nick van der Burgt
Author-email: nick.van.der.burgt@elaad.nl
Requires-Python: >=3.12, <4
Classifier: Programming Language :: Python :: 3
Classifier: Programming Language :: Python :: 3.12
Classifier: Programming Language :: Python :: 3.13
Classifier: Programming Language :: Python :: 3.14
Requires-Dist: openadr3-client (>=1.0.0a1,<2.0.0)
Requires-Dist: pycountry (>=24.6.1,<25.0.0)
Requires-Dist: pydantic (>=2.11.2,<3.0.0)
